ponty/__init__.py
ponty/errors.py
ponty/py.typed
ponty/registry.py
ponty/types_.py
ponty/utils.py
ponty/http/__init__.py
ponty/http/client.py
ponty/http/go.py
ponty/http/render.py
ponty/http/response.py
ponty/http/routes.py
ponty/http/expect/__init__.py
ponty/http/expect/body.py
ponty/http/expect/header.py
ponty/http/expect/query.py
ponty/http/expect/req.py
ponty/http/expect/route.py
ponty/http/schema/__init__.py
ponty/http/schema/build.py
ponty/memo/__init__.py
ponty/memo/cache/__init__.py
ponty/memo/cache/base.py
ponty/memo/cache/local.py
ponty/memo/cache/stats.py
ponty/memo/lock/__init__.py
ponty/memo/lock/base.py
ponty/memo/lock/local.py
ponty-0.3.9.dist-info/METADATA
ponty-0.3.9.dist-info/WHEEL
ponty-0.3.9.dist-info/top_level.txt
ponty-0.3.9.dist-info/RECORD
